emojipedia/__init__.py
emojipedia/emoji.py
emojipedia/emojipedia.py
Emojipedia-0.4.0.dist-info/LICENSE
Emojipedia-0.4.0.dist-info/METADATA
Emojipedia-0.4.0.dist-info/WHEEL
Emojipedia-0.4.0.dist-info/top_level.txt
Emojipedia-0.4.0.dist-info/RECORD
